odoo/addons/product_harmonized_system_delivery/README.rst
odoo/addons/product_harmonized_system_delivery/__init__.py
odoo/addons/product_harmonized_system_delivery/__manifest__.py
odoo/addons/product_harmonized_system_delivery/i18n/es.po
odoo/addons/product_harmonized_system_delivery/i18n/fr.po
odoo/addons/product_harmonized_system_delivery/i18n/hr.po
odoo/addons/product_harmonized_system_delivery/i18n/it.po
odoo/addons/product_harmonized_system_delivery/i18n/product_harmonized_system_delivery.pot
odoo/addons/product_harmonized_system_delivery/models/__init__.py
odoo/addons/product_harmonized_system_delivery/models/product_template.py
odoo/addons/product_harmonized_system_delivery/readme/CONTRIBUTORS.md
odoo/addons/product_harmonized_system_delivery/readme/CREDITS.md
odoo/addons/product_harmonized_system_delivery/readme/DESCRIPTION.md
odoo/addons/product_harmonized_system_delivery/static/description/icon.png
odoo/addons/product_harmonized_system_delivery/static/description/index.html
odoo/addons/product_harmonized_system_delivery/tests/__init__.py
odoo/addons/product_harmonized_system_delivery/tests/test_product_template_fields.py
odoo/addons/product_harmonized_system_delivery/views/product_template.xml
odoo_addon_product_harmonized_system_delivery-19.0.1.0.0.3.dist-info/METADATA
odoo_addon_product_harmonized_system_delivery-19.0.1.0.0.3.dist-info/WHEEL
odoo_addon_product_harmonized_system_delivery-19.0.1.0.0.3.dist-info/top_level.txt
odoo_addon_product_harmonized_system_delivery-19.0.1.0.0.3.dist-info/RECORD
